python_sch_api/__init__.py
python_sch_api-0.0.1.dist-info/LICENSE
python_sch_api-0.0.1.dist-info/METADATA
python_sch_api-0.0.1.dist-info/WHEEL
python_sch_api-0.0.1.dist-info/top_level.txt
python_sch_api-0.0.1.dist-info/RECORD
