Metadata-Version: 2.2
Name: python_sch_api
Version: 0.0.1
Summary: Python 3 пакет для взаимодействия с sch-api
Author-email: Semyon Terebenin <semenchik02@gmail.com>
License:                     GNU GENERAL PUBLIC LICENSE
Project-URL: Homepage, http://gitea.shgpi/aneri/pypi-sch-api
Project-URL: Issues, http://gitea.shgpi/aneri/pypi-sch-api/issues
Classifier: Programming Language :: Python :: 3
Classifier: Operating System :: OS Independent
Requires-Python: >=3.8
License-File: LICENSE
Requires-Dist: requests
